{
    "section-main" : {
        "headline" : {
            "titlecaption": "Open-Source-Projekt für Corona-Warn-App",
            "title": "Helft uns, die Corona-Warn-App zu verbessern"
        },
        "content": {
            "text": "Die Corona-Warn-App ist eine App, die hilft, Infektionsketten des SARS-CoV-2 (COVID-19-Auslöser) in Deutschland nachzuverfolgen und zu unterbrechen. Die App basiert auf Technologien mit einem dezentralisierten Ansatz und informiert Personen, wenn sie mit einer infizierten Person in Kontakt standen. Transparenz ist von entscheidender Bedeutung, um die Bevölkerung zu schützen und die Akzeptanz zu erhöhen.",
            "button": {
                "title": "GitHub aufrufen",
                "url": "https://github.com/corona-warn-app",
                "icon": "github",
                "external": true
            },
            "links" : [
                { "title": "Datenschutz & Sicherheit", "url": "#privacy"},
                { "title": "Unsere Partner", "url": "#partners"}
            ]
        },
        "image": {
            "url" : "/assets/img/app-mockup@2x.png",
            "url-webp": "/assets/img/app-mockup@2x.webp",
            "title": "Corona Warn App"
        }
    },
    "section-image-ticker": {
        "headline": {
            "title": "Wie funktioniert die App?"
        },
        "image-ticker": [
            {
                "index": "01.",
                "image": {"url": "/assets/img/how-it-works-1.svg"},
                "title": "IDs in der Nähe sammeln",
                "text": "Das Exposure Notification Framework (von Apple und Google) auf einem mobilen Gerät sendet einen regelmäßig wechselnden Code (sogenannte Rolling Proximity IDs) und sucht gleichzeitig mithilfe von Bluetooth Low Energy nach IDs anderer Smartphones und speichert die IDs lokal. Die IDs sind nur für 10 bis 20 Minuten gültig und werden kryptografisch von temporären Schlüsseln abgeleitet, die sich alle 24 Stunden ändern.",
                "button": {
                    "title": "Zu kompliziert? Hier gibt es ein einfaches Erklärvideo.",
                    "url": "https://www.bundesregierung.de/breg-de/themen/corona-warn-app/corona-warn-app-erklaerfilm-1758828",
                    "external": true
                }
            },
            {
                "index": "02.",
                "image": {"url": "/assets/img/how-it-works-2.svg", "right" : true },
                "title": "Testergebnis von Personen mit Symptomen mitteilen (optional)",
                "text": "Wenn das jeweilige Labor den elektronischen Prozess unterstützt, können getestete Personen mit dem QR-Code, den sie während des Tests erhalten haben, ihre Ergebnisse abrufen."
            },
            {
                "index": "03.",
                "image": {"url": "/assets/img/how-it-works-3.svg"},
                "title": "Liste von Schlüsseln der als infiziert gemeldeten Personen verteilen",
                "text": "Im Falle eines positiven Testergebnisses werden Personen gebeten, ihre temporären Schlüssel der letzten 14 Tage auf den Server hochzuladen. Um Missbrauch zu verhindern, verifiziert das Backend der Corona-Warn-App zuerst das positive Testergebnis. Bei einer Bestätigung fügt der Server die temporären Schlüssel in eine Liste ein, die regelmäßig an alle Apps gesendet wird."
            },
            {
                "index": "04.",
                "image": {"url": "/assets/img/how-it-works-4.svg","right": true },
                "title": "Prüfung auf Kontakt mit Personen, die sich als infiziert gemeldet haben",
                "text": "Nachdem ein mobiles Gerät die Liste aller vorhandenen Schlüssel der Personen heruntergeladen hat, die positiv getestet wurden, leitet das Exposure Notification Framework die jeweiligen IDs ab und prüft lokal, ob diese den lokal gesammelten Rolling Proximity Identifiern entsprechen. Im Kontaktfall wird das Risiko eingeschätzt und die Person erhält entsprechende Handlungsanweisungen.",
                "button": {"title": "Weitere Infos im Scoping-Dokument", "url": "https://github.com/corona-warn-app/cwa-documentation/blob/master/translations/scoping_document.de.md", "external": true}
            }
        ]
    },
    "section-boxes": {
        "headline" : {
            "title": "Bleib auf dem Laufenden!"
        },
        "boxes" : [
            {
                "image": {"url": "/assets/img/news-blog.svg"},
                "titlecaption": "Stay tuned!",
                "title": "Corona-Warn-App Open-Source-Blog in Kürze verfügbar"
            },
            {
                "image": {
                    "url": "/assets/img/faq.svg"
                },
                "title": "Noch Fragen?",
                "links": [{
                    "url": "/de/faq/",
                    "title": "Hier geht‘s zu den FAQs",
                    "class": "btn-link btn-link-icon btn-link-icon_right"
                }]
            }
        ],
        "slider": {
            "target": "news",
            "button": {
                "title": "Alle News",
                "url": "/de/aktuelles/"
            },
            "amount": 3
        }
    },
    "section-image-text": {
        "image": {
            "url" : "/assets/img/running-app.svg",
            "title": "Beispiel Quellcode"
        },
        "headline": {
            "title": "Mach mit beim Open-Source-Projekt!",
            "textblock": [
                "Wenn Du an dem Projekt mitarbeiten möchtest, kannst Du zu GitHub wechseln und sofort loslegen. Hier kannst Du Dir auch die <a href='https://github.com/corona-warn-app/cwa-documentation' target='_blank' rel='noopener noreferrer'>Dokumentation</a> durchlesen, den <a href='https://github.com/corona-warn-app/cwa-documentation/blob/master/CODE_OF_CONDUCT.md' target='_blank' rel='noopener noreferrer'>Code of Conduct</a> einsehen und mehr darüber erfahren, wie Du in der <a href='/de/community/'>Community</a> mitarbeiten kannst."
            ],
            "button": {
                "title": "Mach mit in GitHub",
                "url": "https://github.com/corona-warn-app/",
                "icon": "github",
                "external": true
            }
        }
    },
    "section-feature-listing" : {
        "id": "privacy",
        "headline" : {
            "title" : "Unsere Grundsätze für Datenschutz und Sicherheit"
        },
        "feature-list": [{
            "image" : {
                "url": "/assets/img/icons/open-source.svg",
                "title" : "Open Source"
            },
            "headline" : {
                "title" : "Open-Source-Ansatz"
            },
            "list": [{
                "title": "Transparenz",
                "text" : "Nur durch Transparenz gewinnen wir das Vertrauen der Bevölkerung und erhöhen die Akzeptanz der App. Unser <a href='https://github.com/corona-warn-app/cwa-documentation/blob/master/solution_architecture.md' target='_blank' rel='noopener noreferrer'>Architektur-Dokument (Englisch)</a> und die <a href='/assets/documents/cwa-eula-de.pdf' target='_blank' rel='noopener noreferrer'>Nutzungsbedingungen</a> sind offen einsehbar."
                },{
                "title": "Die Community",
                "text": "Die Community trägt zu mehr Sicherheit und Datenschutz bei, da die Community-Mitglieder Probleme frühzeitig erkennen und bei deren Lösung unterstützen können."
                }]
        },{
            "image" : {
                "url": "/assets/img/icons/decentralized.svg",
                "title" : "Datenschutz"
            },
            "headline" : {
                "title" : "Datenschutz"
            },
            "list": [{
                "title": "Dezentraler Ansatz",
                "text" : "Die Architektur beruht wie die Protokolle <a href='https://github.com/DP-3T/documents' target='_blank' rel='noopener noreferrer' title=''>DP-3T</a> und <a href='https://tcn-coalition.org/' target='_blank' rel='noopener noreferrer' title=''>TCN</a> auf einem dezentralen Ansatz und baut auf den Exposure-Notification-API-Spezifikationen von Apple und Google auf."
                },{
                "title": "Zwei Zwecke",
                "text": "Es werden nur personenbezogene Daten verarbeitet, die für die folgenden beiden Zwecke erforderlich sind:<br>1. zur Beurteilung des persönlichen Infektionsrisikos<br>2. zur schnelleren Übermittlung des SARS-CoV-2-Testergebnisses"
                },{
                "title": "Datenschutzdokument",
                "text": "Einzelheiten werden in der <a href='/assets/documents/cwa-privacy-notice-de.pdf'>Datenschutzerklärung des Robert Koch-Instituts</a> näher dargelegt. Weitere Details finden Sie in der <a href='/assets/documents/cwa-datenschutz-folgenabschaetzung.pdf'>Datenschutz-Folgenabschätzung</a> sowie den zugehörigen Anlagen <a href='/assets/documents/cwa-datenschutz-folgenabschaetzung-anlage1.pdf'>1</a>, <a href='/assets/documents/cwa-datenschutz-folgenabschaetzung-anlage2.pdf'>2</a>, <a href='/assets/documents/cwa-datenschutz-folgenabschaetzung-anlage3.pdf'>3</a>, <a href='/assets/documents/cwa-datenschutz-folgenabschaetzung-anlage4.pdf'>4</a> und <a href='/assets/documents/cwa-datenschutz-folgenabschaetzung-anlage5.pdf'>5</a>."
                },{
                "title": "Im Design-Prozess",
                "text": "Im Design-Prozess wird für jeden Schritt sichergestellt, dass die App möglichst wenige der benötigten personenbezogenen Daten verarbeitet und für diese Daten ein größtmöglicher Schutz besteht."
                }]
        },{
            "image" : {
                "url": "/assets/img/icons/lock.svg",
                "title" : "Sicherheit"
            },
            "headline" : {
                "title" : "Sicherheit"
            },
            "list": [{
                "title": "Offen und transparent",
                "text": "Das Prinzip „Security through obscurity“, bei dem die Sicherheit eines Systems durch die Geheimhaltung seiner Funktionsweise gewährleistet wird, greift bei diesem Projekt nicht: Wir verfolgen einen offenen und transparenten Ansatz."
            }, {
                "title": "Secure Software Development Lifecycle",
                "text": "Die Sicherheit der Anwendungsentwicklung wird durch den Secure Software Development Lifecycle gewährleistet. Dieser umfasst unter anderem die Modellierung von Bedrohungen (Threat Modeling), eine durchgängige Risikobewertung, die Sicherheitsplanung sowie Sicherheits- und Penetrationstests."
            }, {
                "title": "Hosting",
                "text": "Das Hosting entspricht BSI C5, SOC 2 und SOC1/ISAE 3402."
            }]
        }],
        "content": {
            "button": {
                "title": "Siehe Details in der Dokumentation",
                "icon": "github",
                "url": "https://github.com/corona-warn-app/cwa-documentation/",
                "external": true
            }
        }
    },
    "section-icon-listing": {
        "id": "partners",
        "headline" : {
            "title": "Unsere Partnerinnen und Partner",
            "text": "Anfang Mai 2020 hat die Bundesregierung SAP und die Deutsche-Telekom-Tochter T-Systems gebeten, die offizielle Corona-Warn-App für Deutschland zu entwickeln. Die App soll nach dem Open-Source-Prinzip entwickelt werden und auf einem dezentralen Ansatz basieren. Folgende Partner unterstützen die Entwicklung der App, in die auch die globale Open-Source-Community eingebunden ist:"
        },
        "icon-list" : [{
                "icon-url": "/assets/img/partner/bcg_logo.svg",
                "title": "Boston Consulting Group"
            },{
                "icon-url": "/assets/img/partner/bcgdv_logo.svg",
                "title": "BCG Digital Ventures"
            },{
                "icon-url": "/assets/img/partner/cispa_logo@1x.png",
                "icon-set": "/assets/img/partner/cispa_logo@1x.png 1x, /assets/img/partner/cispa_logo@2x.png 2x",
                "title": "Cispa"
            },{
                "icon-url": "/assets/img/partner/detecon-logo@1x.png",
                "icon-set": "/assets/img/partner/detecon-logo@1x.png 1x, /assets/img/partner/detecon-logo@2x.png 2x",
                "title": "Detecon"
            }, {
                "icon-url": "/assets/img/partner/fraunhofer_logo.svg",
                "title": "Fraunhofer Institut"
            }, {
                "icon-url": "/assets/img/partner/HealthyTogehter_logo.svg",
                "title": "Healthy Together"
            }, {
                "icon-url": "/assets/img/partner/Helmholtz_logo.svg",
                "title": "Helmholtz"
            }, {
                "icon-url": "/assets/img/partner/logo_msg@1x.png",
                "icon-set": "/assets/img/partner/logo_msg@1x.png 1x, /assets/img/partner/logo_msg@2x.png 2x",
                "title": "msg systems ag"
            }, {
                "icon-url": "/assets/img/partner/rki-logo@1x.png",
                "icon-set": "/assets/img/partner/rki-logo@1x.png 1x, /assets/img/partner/rki-logo@2x.png 2x",
                "title": "Robert Koch Institut"
            }, {
                "icon-url": "/assets/img/partner/sap_logo@1x.png",
                "icon-set": "/assets/img/partner/sap_logo@1x.png 1x, /assets/img/partner/sap_logo@2x.png 2x",
                "title": "SAP"
            }, {
                "icon-url": "/assets/img/partner/T_Logo.svg",
                "title": "Telecom"
            },{
                "icon-url": "/assets/img/partner/TUViT_logo@1x.png",
                "icon-set": "/assets/img/partner/TUViT_logo@1x.png 1x, /assets/img/partner/TUViT_logo@2x.png 2x",
                "title": "TÜViT"
            }
        ]
    },
    "section-join-project": {
        "headline" : {
            "title": "Mach mit beim Open-Source-Projekt!",
            "button": {
                "url": "https://github.com/corona-warn-app",
                "title": "GitHub aufrufen",
                "external": true,
                "icon": "github"
            }
        },
        "box" : {
            "image": {
                "url": "/assets/img/faq.svg",
                "title": "FAQ"
            },
            "content": {
                "title": "Mehr Fragen?",
                "links": [{
                    "title": "Hier geht‘s zu den FAQs",
                    "url": "/de/faq/"
                }]
            }
        },
        "content": {
            "close-btn": {
                "title": "App Dialog schließen"
            },
            "icon-list": [
                {
                    "url": "https://apps.apple.com/de/app/corona-warn-app/id1512595757",
                    "icon-url": "/assets/img/App_Store_Badge_US-UK.svg",
                    "title": "Apple App Store",
                    "external": true
                },
                {
                    "url": "https://play.google.com/store/apps/details?id=de.rki.coronawarnapp",
                    "icon-url": "/assets/img/google-play-badge.svg",
                    "title": "Google Play Store",
                    "external": true
                }
            ],
            "headline" : {
                "title": "App mit!",
                "text": "Jetzt zum Download verfügbar im <span class='nobr'>Apple App Store</span> und auf <span class='nobr'>Google Play</span>."
            }
        }
    },
    "section-soon-available": {
        "headline": {
            "titlecaption": "Stay tuned!",
            "title": "Die Corona-Warn-App steht bald zum Download bereit."
        }
    }
}
